README
setup.py
saimmutable/__init__.py
saimmutable.egg-info/PKG-INFO
saimmutable.egg-info/SOURCES.txt
saimmutable.egg-info/dependency_links.txt
saimmutable.egg-info/not-zip-safe
saimmutable.egg-info/requires.txt
saimmutable.egg-info/top_level.txt