Metadata-Version: 1.0
Name: saimmutable
Version: 0.2
Summary: SA instrumentation machinery for immutable data models
Home-page: UNKNOWN
Author: Andrey Popp
Author-email: 8mayday@gmail.com
License: BSD
Platform: UNKNOWN
